ds_py_version_demo/__init__.py
ds_py_version_demo-0.0.10.dist-info/LICENSE
ds_py_version_demo-0.0.10.dist-info/METADATA
ds_py_version_demo-0.0.10.dist-info/WHEEL
ds_py_version_demo-0.0.10.dist-info/top_level.txt
ds_py_version_demo-0.0.10.dist-info/RECORD
